aio_cooker_client/__init__.py
aio_cooker_client/client.py
aio_cooker_client-0.1.0.dist-info/LICENSE
aio_cooker_client-0.1.0.dist-info/METADATA
aio_cooker_client-0.1.0.dist-info/WHEEL
aio_cooker_client-0.1.0.dist-info/top_level.txt
aio_cooker_client-0.1.0.dist-info/RECORD
